benchline/__init__.py
benchline/args.py
benchline/async.py
benchline/binary.py
benchline/command.py
benchline/countdown_generator.py
benchline/date_diff.py
benchline/files.py
benchline/hours_seconds_2_hours.py
benchline/http_format.py
benchline/input.py
benchline/jaxrs_ws_counter.py
benchline/new_setup_py.py
benchline/parse_miredot_tree.py
benchline/python_deploy.py
benchline/python_install.py
benchline/save_line_counts.py
benchline/sum_timelog.py
benchline/timer.py
benchline/user_input.py
benchline/new_python_file/__init__.py
benchline/new_python_file/new_python_file.py
benchline/test/__init__.py
benchline/test/test_benchline.py
benchline-0.5.3.data/data/LICENSE
benchline-0.5.3.data/data/README.md
benchline-0.5.3.data/data/benchline/new_python_file/new_class_file.tmpl
benchline-0.5.3.data/data/benchline/new_python_file/new_cmd_file.tmpl
benchline-0.5.3.data/data/benchline/new_python_file/new_python_file.tmpl
benchline-0.5.3.data/scripts/countdown_generator
benchline-0.5.3.data/scripts/date_diff
benchline-0.5.3.data/scripts/hours_seconds_2_hours
benchline-0.5.3.data/scripts/jaxrs_ws_counter
benchline-0.5.3.data/scripts/new_python_file
benchline-0.5.3.data/scripts/new_setup_py
benchline-0.5.3.data/scripts/parse_miredot_tree
benchline-0.5.3.data/scripts/python_deploy
benchline-0.5.3.data/scripts/python_install
benchline-0.5.3.data/scripts/save_line_counts
benchline-0.5.3.data/scripts/sum_timelog
benchline-0.5.3.dist-info/DESCRIPTION.rst
benchline-0.5.3.dist-info/entry_points.txt
benchline-0.5.3.dist-info/METADATA
benchline-0.5.3.dist-info/pydist.json
benchline-0.5.3.dist-info/RECORD
benchline-0.5.3.dist-info/top_level.txt
benchline-0.5.3.dist-info/WHEEL
