Metadata-Version: 2.0
Name: benchline
Version: 0.5.3
Summary: Modules for important things I don't want to reinvent over and over again.
Home-page: https://github.com/pauldeden/benchline
Author: Paul D. Eden
Author-email: paul@benchline.org
License: MIT
Platform: UNKNOWN
Requires-Dist: requests
Requires-Dist: simplejson
Requires-Dist: decorator
Requires-Dist: ago
Requires-Dist: six
Requires-Dist: peewee
Requires-Dist: toolz
